dev_insights/__init__.py
dev_insights/config.py
dev_insights/formatters.py
dev_insights/middleware.py
dev_insights/sql_trace.py
dev_insights/trace.py
dev_insights/collectors/__init__.py
dev_insights/collectors/connection.py
dev_insights/collectors/db.py
django_dev_insights-0.2.1.dist-info/licenses/LICENSE
django_dev_insights-0.2.1.dist-info/METADATA
django_dev_insights-0.2.1.dist-info/WHEEL
django_dev_insights-0.2.1.dist-info/top_level.txt
django_dev_insights-0.2.1.dist-info/RECORD
